ALMAFE_ConfigDelivery-0.0.2.data/data/ConfigDelivery_template.ini
ConfigDelivery/__init__.py
ConfigDelivery/CCA6/CCA6Database.py
ConfigDelivery/CCA6/DataDelivery.py
ConfigDelivery/CCA6/DeliveryConfig.py
ConfigDelivery/CCA6/LoadConfiguration.py
ConfigDelivery/CCA6/__init__.py
ConfigDelivery/CCA6/ConfigFiles/AmplitudeStability.ini
ConfigDelivery/CCA6/ConfigFiles/Beam Patterns Excel.ini
ConfigDelivery/CCA6/ConfigFiles/CoPol Beam Patterns FarField.ini
ConfigDelivery/CCA6/ConfigFiles/Cross Polarization OLD Excel method.ini
ConfigDelivery/CCA6/ConfigFiles/Cross Polarization.ini
ConfigDelivery/CCA6/ConfigFiles/Deliverables Configuration.ini
ConfigDelivery/CCA6/ConfigFiles/IF_Spectrum.ini
ConfigDelivery/CCA6/ConfigFiles/Image Rejection.ini
ConfigDelivery/CCA6/ConfigFiles/Inband Power.ini
ConfigDelivery/CCA6/ConfigFiles/Noise Temperature.ini
ConfigDelivery/CCA6/ConfigFiles/PhaseDrift.ini
ConfigDelivery/CCA6/ConfigFiles/Polarization Accuracy.ini
ConfigDelivery/CCA6/ConfigFiles/Power Variation.ini
ConfigDelivery/CCA6/ConfigFiles/Total Power.ini
ConfigDelivery/CCA6/ConfigFiles/XPol Beam Patterns Excel.ini
ConfigDelivery/CCA6/ConfigFiles/XPol Beam Patterns FarField.ini
ConfigDelivery/CCA6/ConfigFiles/__init__.py
ConfigDelivery/FEMC/FEMCMakeIniFile.py
ConfigDelivery/FEMC/__init__.py
ConfigDelivery/Plot/WCA.py
ConfigDelivery/Plot/__init__.py
ConfigDelivery/WCA/LoadConfiguration.py
ConfigDelivery/WCA/WCADataFiles.py
ConfigDelivery/WCA/WCADatabase.py
ConfigDelivery/WCA/WCAOutputPower.py
ConfigDelivery/WCA/__init__.py
FETMSDatabase/LoadConfiguration.py
FETMSDatabase/TestDataHeader.py
FETMSDatabase/__init__.py
tests/__init__.py
tests/Integration/FixMissingWCAs.py
tests/Integration/MakeAllWCAData.py
tests/Integration/__init__.py
tests/UnitTests/__init__.py
ALMAFE_ConfigDelivery-0.0.2.dist-info/LICENSE
ALMAFE_ConfigDelivery-0.0.2.dist-info/METADATA
ALMAFE_ConfigDelivery-0.0.2.dist-info/WHEEL
ALMAFE_ConfigDelivery-0.0.2.dist-info/top_level.txt
ALMAFE_ConfigDelivery-0.0.2.dist-info/RECORD
