Metadata-Version: 2.1
Name: ALMAFE-ConfigDelivery
Version: 0.0.2
Summary: Classes for retrieval and transformation of ALMA Front End subassembly configuration data
Home-page: https://github.com/morganmcleod
Author: Morgan McLeod
Author-email: mmcleod@nrao.edu
License: UNKNOWN
Platform: UNKNOWN
Classifier: Programming Language :: Python :: 3
Classifier: License :: OSI Approved :: GNU Lesser General Public License v2 or later (LGPLv2+)
Classifier: Operating System :: OS Independent
Requires-Python: >=3.6
Requires-Dist: ALMAFE-Lib (>=0.0.2)
Requires-Dist: plotly (>=4.9.0)
Requires-Dist: pandas (>=1.1.3)
Requires-Dist: psutil (>=5.7.2)
